ssb_plotly_template/__init__.py
ssb_plotly_template/__main__.py
ssb_plotly_template/py.typed
ssb_plotly_template/ssb_plotly_template.py
ssb_plotly_template-0.0.1.dist-info/LICENSE
ssb_plotly_template-0.0.1.dist-info/METADATA
ssb_plotly_template-0.0.1.dist-info/WHEEL
ssb_plotly_template-0.0.1.dist-info/entry_points.txt
ssb_plotly_template-0.0.1.dist-info/RECORD
