Metadata-Version: 2.1
Name: ssb-plotly-template
Version: 0.0.1
Summary: Plotly template SSB design
Home-page: https://github.com/statisticsnorway/ssb-plotly-template
License: MIT
Author: Elise Alstad
Author-email: elise.alstad@ssb.no
Requires-Python: >=3.10,<4.0
Classifier: Development Status :: 3 - Alpha
Classifier: License :: OSI Approved :: MIT License
Classifier: Programming Language :: Python :: 3
Classifier: Programming Language :: Python :: 3.10
Classifier: Programming Language :: Python :: 3.11
Classifier: Programming Language :: Python :: 3.12
Classifier: Programming Language :: Python :: 3.13
Requires-Dist: click (>=8.0.1)
Requires-Dist: plotly (>=5.24.1,<6.0.0)
Project-URL: Changelog, https://github.com/statisticsnorway/ssb-plotly-template/releases
Project-URL: Documentation, https://statisticsnorway.github.io/ssb-plotly-template
Project-URL: Repository, https://github.com/statisticsnorway/ssb-plotly-template
